.gitignore
CHANGES.rst
MANIFEST.in
README.rst
README.txt
bootstrap.py
buildout.cfg
setup.py
docs/LICENSE.GPL
docs/LICENSE.txt
smtp2zope/__init__.py
smtp2zope/config.py
smtp2zope/locking.py
smtp2zope/script.py
smtp2zope.egg-info/PKG-INFO
smtp2zope.egg-info/SOURCES.txt
smtp2zope.egg-info/dependency_links.txt
smtp2zope.egg-info/entry_points.txt
smtp2zope.egg-info/not-zip-safe
smtp2zope.egg-info/requires.txt
smtp2zope.egg-info/top_level.txt