Metadata-Version: 1.0
Name: smtp2zope
Version: 1.2
Summary: Read an email from stdin and forward it to a url
Home-page: https://github.com/collective/smtp2zope
Author: Maurits van Rees
Author-email: maurits@vanrees.org
License: GPL
Platform: UNKNOWN
Classifier: Programming Language :: Python
Classifier: Topic :: Communications :: Email
